{
	"name": "Bkg_Habs",
	"plugin-id": "Sprite",
	"sid": 428365671514013,
	"isGlobal": false,
	"editorNewInstanceIsReplica": true,
	"instanceVariables": [],
	"behaviorTypes": [],
	"effectTypes": [],
	"animations": {
		"items": [
			{
				"frames": [
					{
						"width": 235,
						"height": 72,
						"originX": 0.5,
						"originY": 0.5,
						"originalSource": "",
						"exportFormat": "lossless",
						"exportQuality": 0.8,
						"fileType": "image/png",
						"imageSpriteId": 2024239,
						"collisionPoly": {
							"points": [
								0.01020408163265306,
								0,
								1,
								0.02830188679245283,
								0.9897959183673469,
								1,
								0,
								0.9716981132075472
							]
						},
						"useCollisionPoly": true,
						"duration": 1,
						"tag": ""
					},
					{
						"width": 296,
						"height": 72,
						"originX": 0.5,
						"originY": 0.5,
						"originalSource": "",
						"exportFormat": "lossless",
						"exportQuality": 0.8,
						"fileType": "image/png",
						"imageSpriteId": 863923,
						"collisionPoly": {
							"points": [
								0.10810810810810811,
								0,
								0.9898648648648649,
								0,
								1,
								0.041666666666666664,
								1,
								0.9583333333333334,
								0.9898648648648649,
								1,
								0.10810810810810811,
								1,
								0,
								0.5416666666666666,
								0.0033783783783783786,
								0.4305555555555556
							]
						},
						"useCollisionPoly": true,
						"duration": 1,
						"tag": ""
					},
					{
						"width": 296,
						"height": 72,
						"originX": 0.5,
						"originY": 0.5,
						"originalSource": "",
						"exportFormat": "lossless",
						"exportQuality": 0.8,
						"fileType": "image/png",
						"imageSpriteId": 2439116,
						"collisionPoly": {
							"points": [
								0.10810810810810811,
								0,
								0.9898648648648649,
								0,
								1,
								0.041666666666666664,
								1,
								0.9583333333333334,
								0.9898648648648649,
								1,
								0.10810810810810811,
								1,
								0,
								0.5416666666666666,
								0.0033783783783783786,
								0.4305555555555556
							]
						},
						"useCollisionPoly": true,
						"duration": 1,
						"tag": ""
					},
					{
						"width": 357,
						"height": 72,
						"originX": 0.5,
						"originY": 0.5,
						"originalSource": "",
						"exportFormat": "lossless",
						"exportQuality": 0.8,
						"fileType": "image/png",
						"imageSpriteId": 629703,
						"collisionPoly": {
							"points": [
								0.0896358543417367,
								0,
								0.9915966386554622,
								0,
								1,
								0.041666666666666664,
								1,
								0.9583333333333334,
								0.9915966386554622,
								1,
								0.0896358543417367,
								1,
								0,
								0.5416666666666666,
								0.0028011204481792717,
								0.4305555555555556
							]
						},
						"useCollisionPoly": true,
						"duration": 1,
						"tag": ""
					}
				],
				"sid": 915623348907054,
				"name": "Animation 1",
				"isLooping": false,
				"isPingPong": false,
				"repeatCount": 1,
				"repeatTo": 0,
				"speed": 0
			}
		],
		"subfolders": []
	}
}